<?xml version="1.0" encoding="utf-8" ?><dwsync><file name="Base.php" server="sftp.domeneshop.no/www/Josefin/wordpress/" local="3516642389" remote="3516642389" Dst="-1" /><file name="DB.php" server="sftp.domeneshop.no/www/Josefin/wordpress/" local="3516642389" remote="3516642389" Dst="-1" /><file name="File.php" server="sftp.domeneshop.no/www/Josefin/wordpress/" local="3516642389" remote="3516642389" Dst="-1" /><file name="Memcache.php" server="sftp.domeneshop.no/www/Josefin/wordpress/" local="3516642389" remote="3516642389" Dst="-1" /><file name="MySQL.php" server="sftp.domeneshop.no/www/Josefin/wordpress/" local="3516642389" remote="3516642389" Dst="-1" /><file name="Base.php" server="Macintosh HD/Users/paltaulebrentebraten/Documents/Josefin/Test/" local="3516642389" remote="3516642389" Dst="-1" /><file name="File.php" server="Macintosh HD/Users/paltaulebrentebraten/Documents/Josefin/Test/" local="3516642389" remote="3516642389" Dst="-1" /><file name="DB.php" server="Macintosh HD/Users/paltaulebrentebraten/Documents/Josefin/Test/" local="3516642389" remote="3516642389" Dst="-1" /><file name="Memcache.php" server="Macintosh HD/Users/paltaulebrentebraten/Documents/Josefin/Test/" local="3516642389" remote="3516642389" Dst="-1" /><file name="MySQL.php" server="Macintosh HD/Users/paltaulebrentebraten/Documents/Josefin/Test/" local="3516642389" remote="3516642389" Dst="-1" /></dwsync>